exiftool.py
ocrd_pyexiftool-0.2.0.dist-info/DESCRIPTION.rst
ocrd_pyexiftool-0.2.0.dist-info/top_level.txt
ocrd_pyexiftool-0.2.0.dist-info/METADATA
ocrd_pyexiftool-0.2.0.dist-info/RECORD
ocrd_pyexiftool-0.2.0.dist-info/metadata.json
ocrd_pyexiftool-0.2.0.dist-info/WHEEL
